<?xml version="1.0" encoding="UTF-8" standalone="yes"?>
<gpx xmlns="http://www.topografix.com/GPX/1/1" version="1.1" creator="NaviControlCenter" xmlns:xsi="http://www.w3.org/2001/XMLSchema-instance" xsi:schemaLocation="http://www.topografix.com/GPX/1/1 http://www.topografix.com/GPX/1/1/gpx.xsd">
  <metadata>
    <name>NaviControlCenter track export</name>
  </metadata>
  <trk>
    <name>2013/09/13 13:15:09</name>
    <trkseg>
      <trkpt lat="49.41954" lon="8.68826">
        <ele>0</ele>
        <time>2013-09-13T11:15:09Z</time>
      </trkpt>
      <trkpt lat="49.41954" lon="8.68826">
        <ele>0</ele>
        <time>2013-09-13T11:15:10Z</time>
      </trkpt>
      <trkpt lat="49.41943" lon="8.68772">
        <ele>0</ele>
        <time>2013-09-13T11:16:39Z</time>
      </trkpt>
      <trkpt lat="49.41957" lon="8.68721">
        <ele>0</ele>
        <time>2013-09-13T11:16:50Z</time>
      </trkpt>
      <trkpt lat="49.41993" lon="8.68712">
        <ele>0</ele>
        <time>2013-09-13T11:17:02Z</time>
      </trkpt>
      <trkpt lat="49.4203" lon="8.68699">
        <ele>0</ele>
        <time>2013-09-13T11:17:15Z</time>
      </trkpt>
      <trkpt lat="49.42069" lon="8.68692">
        <ele>0</ele>
        <time>2013-09-13T11:17:30Z</time>
      </trkpt>
      <trkpt lat="49.42099" lon="8.68659">
        <ele>0</ele>
        <time>2013-09-13T11:17:49Z</time>
      </trkpt>
      <trkpt lat="49.42119" lon="8.68611">
        <ele>0</ele>
        <time>2013-09-13T11:18:03Z</time>
      </trkpt>
      <trkpt lat="49.42154" lon="8.68592">
        <ele>0</ele>
        <time>2013-09-13T11:18:15Z</time>
      </trkpt>
      <trkpt lat="49.42191" lon="8.68567">
        <ele>0</ele>
        <time>2013-09-13T11:18:33Z</time>
      </trkpt>
      <trkpt lat="49.42225" lon="8.68548">
        <ele>0</ele>
        <time>2013-09-13T11:18:40Z</time>
      </trkpt>
      <trkpt lat="49.42262" lon="8.68524">
        <ele>0</ele>
        <time>2013-09-13T11:18:49Z</time>
      </trkpt>
      <trkpt lat="49.42297" lon="8.68498">
        <ele>0</ele>
        <time>2013-09-13T11:19:00Z</time>
      </trkpt>
      <trkpt lat="49.42331" lon="8.68479">
        <ele>0</ele>
        <time>2013-09-13T11:19:16Z</time>
      </trkpt>
      <trkpt lat="49.42364" lon="8.68449">
        <ele>0</ele>
        <time>2013-09-13T11:19:24Z</time>
      </trkpt>
      <trkpt lat="49.42397" lon="8.68425">
        <ele>0</ele>
        <time>2013-09-13T11:19:35Z</time>
      </trkpt>
      <trkpt lat="49.42431" lon="8.68398">
        <ele>0</ele>
        <time>2013-09-13T11:19:44Z</time>
      </trkpt>
      <trkpt lat="49.42463" lon="8.68369">
        <ele>0</ele>
        <time>2013-09-13T11:19:54Z</time>
      </trkpt>
      <trkpt lat="49.42496" lon="8.68338">
        <ele>0</ele>
        <time>2013-09-13T11:20:05Z</time>
      </trkpt>
      <trkpt lat="49.4253" lon="8.68308">
        <ele>0</ele>
        <time>2013-09-13T11:20:17Z</time>
      </trkpt>
      <trkpt lat="49.42561" lon="8.6828">
        <ele>0</ele>
        <time>2013-09-13T11:21:03Z</time>
      </trkpt>
      <trkpt lat="49.42594" lon="8.68254">
        <ele>0</ele>
        <time>2013-09-13T11:21:13Z</time>
      </trkpt>
      <trkpt lat="49.42628" lon="8.68224">
        <ele>0</ele>
        <time>2013-09-13T11:21:23Z</time>
      </trkpt>
      <trkpt lat="49.42659" lon="8.68193">
        <ele>0</ele>
        <time>2013-09-13T11:21:33Z</time>
      </trkpt>
      <trkpt lat="49.42693" lon="8.68165">
        <ele>0</ele>
        <time>2013-09-13T11:21:45Z</time>
      </trkpt>
      <trkpt lat="49.42725" lon="8.68134">
        <ele>0</ele>
        <time>2013-09-13T11:21:56Z</time>
      </trkpt>
      <trkpt lat="49.42758" lon="8.68106">
        <ele>0</ele>
        <time>2013-09-13T11:22:06Z</time>
      </trkpt>
      <trkpt lat="49.42794" lon="8.6808">
        <ele>0</ele>
        <time>2013-09-13T11:22:18Z</time>
      </trkpt>
      <trkpt lat="49.4283" lon="8.68059">
        <ele>0</ele>
        <time>2013-09-13T11:22:28Z</time>
      </trkpt>
      <trkpt lat="49.42868" lon="8.68046">
        <ele>0</ele>
        <time>2013-09-13T11:22:38Z</time>
      </trkpt>
      <trkpt lat="49.42903" lon="8.68031">
        <ele>0</ele>
        <time>2013-09-13T11:22:47Z</time>
      </trkpt>
      <trkpt lat="49.42939" lon="8.68018">
        <ele>0</ele>
        <time>2013-09-13T11:22:57Z</time>
      </trkpt>
      <trkpt lat="49.42974" lon="8.67999">
        <ele>0</ele>
        <time>2013-09-13T11:23:25Z</time>
      </trkpt>
      <trkpt lat="49.43008" lon="8.67976">
        <ele>0</ele>
        <time>2013-09-13T11:23:38Z</time>
      </trkpt>
      <trkpt lat="49.43028" lon="8.67929">
        <ele>0</ele>
        <time>2013-09-13T11:23:48Z</time>
      </trkpt>
      <trkpt lat="49.43065" lon="8.67911">
        <ele>0</ele>
        <time>2013-09-13T11:24:00Z</time>
      </trkpt>
      <trkpt lat="49.43104" lon="8.67897">
        <ele>0</ele>
        <time>2013-09-13T11:24:10Z</time>
      </trkpt>
      <trkpt lat="49.43143" lon="8.6789">
        <ele>0</ele>
        <time>2013-09-13T11:24:20Z</time>
      </trkpt>
      <trkpt lat="49.43182" lon="8.67883">
        <ele>0</ele>
        <time>2013-09-13T11:24:30Z</time>
      </trkpt>
      <trkpt lat="49.43218" lon="8.67877">
        <ele>0</ele>
        <time>2013-09-13T11:24:39Z</time>
      </trkpt>
      <trkpt lat="49.43256" lon="8.67858">
        <ele>0</ele>
        <time>2013-09-13T11:24:50Z</time>
      </trkpt>
      <trkpt lat="49.43292" lon="8.67842">
        <ele>0</ele>
        <time>2013-09-13T11:25:00Z</time>
      </trkpt>
      <trkpt lat="49.43329" lon="8.67827">
        <ele>0</ele>
        <time>2013-09-13T11:25:11Z</time>
      </trkpt>
      <trkpt lat="49.43365" lon="8.67815">
        <ele>0</ele>
        <time>2013-09-13T11:25:22Z</time>
      </trkpt>
      <trkpt lat="49.43401" lon="8.678">
        <ele>0</ele>
        <time>2013-09-13T11:25:33Z</time>
      </trkpt>
      <trkpt lat="49.43437" lon="8.67784">
        <ele>0</ele>
        <time>2013-09-13T11:25:44Z</time>
      </trkpt>
      <trkpt lat="49.43471" lon="8.67767">
        <ele>0</ele>
        <time>2013-09-13T11:25:54Z</time>
      </trkpt>
      <trkpt lat="49.43506" lon="8.67742">
        <ele>0</ele>
        <time>2013-09-13T11:26:04Z</time>
      </trkpt>
      <trkpt lat="49.43538" lon="8.67716">
        <ele>0</ele>
        <time>2013-09-13T11:26:15Z</time>
      </trkpt>
      <trkpt lat="49.43572" lon="8.67684">
        <ele>0</ele>
        <time>2013-09-13T11:26:25Z</time>
      </trkpt>
      <trkpt lat="49.43605" lon="8.67658">
        <ele>0</ele>
        <time>2013-09-13T11:26:34Z</time>
      </trkpt>
      <trkpt lat="49.43638" lon="8.67622">
        <ele>0</ele>
        <time>2013-09-13T11:26:44Z</time>
      </trkpt>
      <trkpt lat="49.43668" lon="8.67584">
        <ele>0</ele>
        <time>2013-09-13T11:26:53Z</time>
      </trkpt>
      <trkpt lat="49.43697" lon="8.6755">
        <ele>0</ele>
        <time>2013-09-13T11:27:02Z</time>
      </trkpt>
      <trkpt lat="49.43729" lon="8.67516">
        <ele>0</ele>
        <time>2013-09-13T11:27:12Z</time>
      </trkpt>
      <trkpt lat="49.4376" lon="8.67482">
        <ele>0</ele>
        <time>2013-09-13T11:27:22Z</time>
      </trkpt>
      <trkpt lat="49.43792" lon="8.67446">
        <ele>0</ele>
        <time>2013-09-13T11:27:32Z</time>
      </trkpt>
      <trkpt lat="49.43823" lon="8.67414">
        <ele>0</ele>
        <time>2013-09-13T11:27:42Z</time>
      </trkpt>
      <trkpt lat="49.43853" lon="8.67383">
        <ele>0</ele>
        <time>2013-09-13T11:27:50Z</time>
      </trkpt>
      <trkpt lat="49.43887" lon="8.67351">
        <ele>0</ele>
        <time>2013-09-13T11:27:59Z</time>
      </trkpt>
      <trkpt lat="49.43922" lon="8.67323">
        <ele>0</ele>
        <time>2013-09-13T11:28:08Z</time>
      </trkpt>
      <trkpt lat="49.43952" lon="8.67285">
        <ele>0</ele>
        <time>2013-09-13T11:28:17Z</time>
      </trkpt>
      <trkpt lat="49.43982" lon="8.67251">
        <ele>0</ele>
        <time>2013-09-13T11:28:26Z</time>
      </trkpt>
      <trkpt lat="49.44015" lon="8.67225">
        <ele>0</ele>
        <time>2013-09-13T11:28:35Z</time>
      </trkpt>
      <trkpt lat="49.44049" lon="8.67202">
        <ele>0</ele>
        <time>2013-09-13T11:28:45Z</time>
      </trkpt>
      <trkpt lat="49.4408" lon="8.67169">
        <ele>0</ele>
        <time>2013-09-13T11:30:17Z</time>
      </trkpt>
      <trkpt lat="49.44104" lon="8.67126">
        <ele>0</ele>
        <time>2013-09-13T11:30:56Z</time>
      </trkpt>
      <trkpt lat="49.44133" lon="8.67088">
        <ele>0</ele>
        <time>2013-09-13T11:31:11Z</time>
      </trkpt>
      <trkpt lat="49.4415" lon="8.67039">
        <ele>0</ele>
        <time>2013-09-13T11:31:21Z</time>
      </trkpt>
      <trkpt lat="49.44184" lon="8.67008">
        <ele>0</ele>
        <time>2013-09-13T11:31:33Z</time>
      </trkpt>
      <trkpt lat="49.44199" lon="8.66955">
        <ele>0</ele>
        <time>2013-09-13T11:31:46Z</time>
      </trkpt>
      <trkpt lat="49.44234" lon="8.66936">
        <ele>0</ele>
        <time>2013-09-13T11:31:57Z</time>
      </trkpt>
      <trkpt lat="49.44268" lon="8.6691">
        <ele>0</ele>
        <time>2013-09-13T11:32:08Z</time>
      </trkpt>
      <trkpt lat="49.44304" lon="8.66893">
        <ele>0</ele>
        <time>2013-09-13T11:32:21Z</time>
      </trkpt>
      <trkpt lat="49.44308" lon="8.66836">
        <ele>0</ele>
        <time>2013-09-13T11:32:41Z</time>
      </trkpt>
      <trkpt lat="49.44295" lon="8.66781">
        <ele>0</ele>
        <time>2013-09-13T11:32:51Z</time>
      </trkpt>
      <trkpt lat="49.44284" lon="8.66724">
        <ele>0</ele>
        <time>2013-09-13T11:33:01Z</time>
      </trkpt>
      <trkpt lat="49.44274" lon="8.6667">
        <ele>0</ele>
        <time>2013-09-13T11:33:10Z</time>
      </trkpt>
      <trkpt lat="49.44261" lon="8.66613">
        <ele>0</ele>
        <time>2013-09-13T11:33:21Z</time>
      </trkpt>
      <trkpt lat="49.44287" lon="8.66574">
        <ele>0</ele>
        <time>2013-09-13T11:33:37Z</time>
      </trkpt>
      <trkpt lat="49.44323" lon="8.66564">
        <ele>0</ele>
        <time>2013-09-13T11:33:53Z</time>
      </trkpt>
      <trkpt lat="49.44359" lon="8.66552">
        <ele>0</ele>
        <time>2013-09-13T11:34:04Z</time>
      </trkpt>
      <trkpt lat="49.44398" lon="8.6654">
        <ele>0</ele>
        <time>2013-09-13T11:34:14Z</time>
      </trkpt>
      <trkpt lat="49.44434" lon="8.66525">
        <ele>0</ele>
        <time>2013-09-13T11:34:23Z</time>
      </trkpt>
      <trkpt lat="49.44472" lon="8.66507">
        <ele>0</ele>
        <time>2013-09-13T11:34:32Z</time>
      </trkpt>
      <trkpt lat="49.4451" lon="8.66487">
        <ele>0</ele>
        <time>2013-09-13T11:34:41Z</time>
      </trkpt>
      <trkpt lat="49.44544" lon="8.66469">
        <ele>0</ele>
        <time>2013-09-13T11:34:49Z</time>
      </trkpt>
      <trkpt lat="49.44584" lon="8.66455">
        <ele>0</ele>
        <time>2013-09-13T11:34:59Z</time>
      </trkpt>
      <trkpt lat="49.44623" lon="8.66447">
        <ele>0</ele>
        <time>2013-09-13T11:35:08Z</time>
      </trkpt>
      <trkpt lat="49.44661" lon="8.66437">
        <ele>0</ele>
        <time>2013-09-13T11:35:17Z</time>
      </trkpt>
      <trkpt lat="49.44697" lon="8.66428">
        <ele>0</ele>
        <time>2013-09-13T11:35:25Z</time>
      </trkpt>
      <trkpt lat="49.44734" lon="8.66418">
        <ele>0</ele>
        <time>2013-09-13T11:35:34Z</time>
      </trkpt>
      <trkpt lat="49.44773" lon="8.6641">
        <ele>0</ele>
        <time>2013-09-13T11:35:43Z</time>
      </trkpt>
      <trkpt lat="49.4481" lon="8.66401">
        <ele>0</ele>
        <time>2013-09-13T11:35:52Z</time>
      </trkpt>
      <trkpt lat="49.44849" lon="8.66391">
        <ele>0</ele>
        <time>2013-09-13T11:36:02Z</time>
      </trkpt>
      <trkpt lat="49.44885" lon="8.66383">
        <ele>0</ele>
        <time>2013-09-13T11:36:10Z</time>
      </trkpt>
      <trkpt lat="49.44922" lon="8.66373">
        <ele>0</ele>
        <time>2013-09-13T11:36:19Z</time>
      </trkpt>
      <trkpt lat="49.4496" lon="8.66363">
        <ele>0</ele>
        <time>2013-09-13T11:36:34Z</time>
      </trkpt>
      <trkpt lat="49.44997" lon="8.66374">
        <ele>0</ele>
        <time>2013-09-13T11:36:43Z</time>
      </trkpt>
      <trkpt lat="49.45033" lon="8.66383">
        <ele>0</ele>
        <time>2013-09-13T11:36:51Z</time>
      </trkpt>
      <trkpt lat="49.45069" lon="8.66391">
        <ele>0</ele>
        <time>2013-09-13T11:37:01Z</time>
      </trkpt>
      <trkpt lat="49.45106" lon="8.66402">
        <ele>0</ele>
        <time>2013-09-13T11:37:13Z</time>
      </trkpt>
      <trkpt lat="49.4513" lon="8.6641">
        <ele>0</ele>
        <time>2013-09-13T11:39:13Z</time>
      </trkpt>
      <trkpt lat="49.4511" lon="8.66457">
        <ele>0</ele>
        <time>2013-09-13T11:40:11Z</time>
      </trkpt>
      <trkpt lat="49.45096" lon="8.66509">
        <ele>0</ele>
        <time>2013-09-13T11:40:21Z</time>
      </trkpt>
      <trkpt lat="49.4508" lon="8.66562">
        <ele>0</ele>
        <time>2013-09-13T11:40:31Z</time>
      </trkpt>
      <trkpt lat="49.45066" lon="8.66616">
        <ele>0</ele>
        <time>2013-09-13T11:40:41Z</time>
      </trkpt>
      <trkpt lat="49.45052" lon="8.6667">
        <ele>0</ele>
        <time>2013-09-13T11:40:51Z</time>
      </trkpt>
      <trkpt lat="49.4504" lon="8.66728">
        <ele>0</ele>
        <time>2013-09-13T11:41:02Z</time>
      </trkpt>
      <trkpt lat="49.45029" lon="8.6678">
        <ele>0</ele>
        <time>2013-09-13T11:41:12Z</time>
      </trkpt>
      <trkpt lat="49.44994" lon="8.66798">
        <ele>0</ele>
        <time>2013-09-13T11:41:22Z</time>
      </trkpt>
      <trkpt lat="49.44955" lon="8.66803">
        <ele>0</ele>
        <time>2013-09-13T11:41:33Z</time>
      </trkpt>
      <trkpt lat="49.44922" lon="8.66828">
        <ele>0</ele>
        <time>2013-09-13T11:41:43Z</time>
      </trkpt>
      <trkpt lat="49.44893" lon="8.66865">
        <ele>0</ele>
        <time>2013-09-13T11:42:02Z</time>
      </trkpt>
      <trkpt lat="49.44875" lon="8.66917">
        <ele>0</ele>
        <time>2013-09-13T11:42:11Z</time>
      </trkpt>
      <trkpt lat="49.44848" lon="8.66953">
        <ele>0</ele>
        <time>2013-09-13T11:43:46Z</time>
      </trkpt>
    </trkseg>
  </trk>
</gpx>
